{
    "ROTATION":[0,0,0],
    "CAMERA":[0,0,-200],
    "AMBIENT":50,
    "OBJECTS":
    [
      {
        "LIGHT":
        {
          "position":[-800,-400,300]
        }
      },
      {
        "SPHERE_sun":
        {
          "color":[255,0,0],
          "center":[-800,0,300],
          "angle":[0,0,0],
          "radius":300,
          "reflection":0,
          "transparency":90
        },
        "SPHERE_earth":
        {
          "color":[255,0,0],
          "center":[-110,0,300],
          "angle":[0,0,0],
          "radius":80,
          "reflection":0
        },
        "SPHERE_mars":
        {
          "color":[255,0,0],
          "center":[100,0,300],
          "angle":[0,0,0],
          "radius":60,
          "reflection":0
        },
        "SPHERE_upiter":
        {
          "color":[255,0,0],
          "center":[350,0,300],
          "angle":[0,0,0],
          "radius":140,
          "reflection":0
        }
      }
    ]
  }
  